easygraphql/__init__.py
easygraphql/easygraphql.py
easygraphql-0.2311.0.dist-info/LICENSE
easygraphql-0.2311.0.dist-info/METADATA
easygraphql-0.2311.0.dist-info/WHEEL
easygraphql-0.2311.0.dist-info/top_level.txt
easygraphql-0.2311.0.dist-info/RECORD
